Metadata-Version: 2.1
Name: libpythonpro-mascaped
Version: 0.2
Summary: Módulo para exemplificar construção de projetos Python no curso PyTools
Home-page: https://github.com/pedro25mascarenhas/libpythonpro
Author: Pedro Mascarenhas
Author-email: pedro25mascarenhas@gmail.com
License: MIT License
Classifier: Development Status :: 2 - Pre-Alpha
Classifier: Environment :: Console
Classifier: Intended Audience :: Developers
Classifier: License :: OSI Approved :: MIT License
Classifier: Operating System :: OS Independent
Classifier: Programming Language :: Python
Classifier: Programming Language :: Python :: 3.11
Classifier: Framework :: Pytest
License-File: LICENSE
